speteval/__init__.py
speteval/constants.py
speteval/decorators.py
speteval/exceptions.py
speteval/filters.py
speteval/interfaces.py
speteval/utils.py
speteval/validators.py
speteval-0.0.1.dist-info/LICENSE
speteval-0.0.1.dist-info/METADATA
speteval-0.0.1.dist-info/WHEEL
speteval-0.0.1.dist-info/top_level.txt
speteval-0.0.1.dist-info/RECORD
