Metadata-Version: 2.1
Name: speteval
Version: 0.0.1
Summary: A useful module
Home-page: UNKNOWN
Author: Mahmoud Salhab
Author-email: mahmoud@salhab.work
License: MIT
Platform: UNKNOWN
Requires-Dist: dill (==0.3.5.1)
Requires-Dist: numpy (==1.22.4)
Requires-Dist: pandarallel (==1.6.1)
Requires-Dist: pandas (==1.4.2)
Requires-Dist: psutil (==5.9.1)
Requires-Dist: python-dateutil (==2.8.2)
Requires-Dist: pytz (==2022.1)
Requires-Dist: six (==1.16.0)
Requires-Dist: sox (==1.4.1)
Requires-Dist: torch (==1.11.0)
Requires-Dist: torchaudio (==0.11.0)
Requires-Dist: typing-extensions (==4.2.0)
